pygabor/discgabor.py
pygabor/spectrogram.py
pygabor/timecausgabor.py
pygabor-0.9.7.dist-info/LICENSE.md
pygabor-0.9.7.dist-info/METADATA
pygabor-0.9.7.dist-info/WHEEL
pygabor-0.9.7.dist-info/RECORD
