Metadata-Version: 2.1
Name: pygabor
Version: 0.9.7
Summary: Gabor transform toolbox for Python.
Home-page: https://github.com/tonylindeberg/pygabor
License: MIT
Author: Tony Lindeberg
Author-email: tony@kth.se
Requires-Python: >=3.7,<4.0
Classifier: License :: OSI Approved :: MIT License
Classifier: Programming Language :: Python :: 3
Classifier: Programming Language :: Python :: 3.7
Classifier: Programming Language :: Python :: 3.8
Classifier: Programming Language :: Python :: 3.9
Classifier: Programming Language :: Python :: 3.10
Classifier: Programming Language :: Python :: 3.11
Classifier: Programming Language :: Python :: 3.12
Requires-Dist: pyscsp (>=0.9.22,<0.10.0)
Requires-Dist: pytempscsp (>=0.9.3,<0.10.0)
Project-URL: Repository, https://github.com/tonylindeberg/pygabor
